achemy/__init__.py
achemy/base.py
achemy/cli.py
achemy/codegen.py
achemy/config.py
achemy/engine.py
achemy/mixins.py
achemy/model.py
achemy/repository.py
achemy/version.py
achemy/demo/amodels.py
achemy-0.3.1.dist-info/METADATA
achemy-0.3.1.dist-info/WHEEL
achemy-0.3.1.dist-info/licenses/LICENSE
achemy-0.3.1.dist-info/RECORD
