Metadata-Version: 2.4
Name: achemy
Version: 0.3.1
Author-email: ant31 <2t.antoine@gmail.com>
License: Apache-2.0
License-File: LICENSE
Requires-Python: <4,>=3.11
Requires-Dist: alembic<2.0.0,>=1.15.2
Requires-Dist: pydantic>=2
Requires-Dist: sqlalchemy>=2
Provides-Extra: all
Requires-Dist: asyncpg; extra == 'all'
Requires-Dist: rich; extra == 'all'
Requires-Dist: typer; extra == 'all'
Provides-Extra: cli
Requires-Dist: rich; extra == 'cli'
Requires-Dist: typer; extra == 'cli'
Provides-Extra: pg
Requires-Dist: asyncpg; extra == 'pg'
